HummingbirdRobot.py
hummingbird_robot/__init__.py
hummingbird_robot/__main__.py
hummingbird_robot/cli.py
hummingbird_robot-0.0.9.dist-info/AUTHORS.rst
hummingbird_robot-0.0.9.dist-info/LICENSE
hummingbird_robot-0.0.9.dist-info/METADATA
hummingbird_robot-0.0.9.dist-info/WHEEL
hummingbird_robot-0.0.9.dist-info/entry_points.txt
hummingbird_robot-0.0.9.dist-info/top_level.txt
hummingbird_robot-0.0.9.dist-info/RECORD
