Metadata-Version: 2.1
Name: hummingbird-robot
Version: 0.0.9
Summary: A robot using Birdbrain Technologies Hummingbird using the hummingbird_joystick/hummingbird_dual_motor_driver packages.
Home-page: https://github.com/fmorton/python-hummingbird-robot
Author: Frank Morton
Author-email: fmorton@base2inc.com
License: MIT
Project-URL: Documentation, https://python-hummingbird-robot.readthedocs.io/
Project-URL: Changelog, https://python-hummingbird-robot.readthedocs.io/en/latest/changelog.html
Project-URL: Issue Tracker, https://github.com/fmorton/python-hummingbird-robot/issues
Classifier: Development Status :: 5 - Production/Stable
Classifier: Intended Audience :: Developers
Classifier: License :: OSI Approved :: MIT License
Classifier: Operating System :: Unix
Classifier: Operating System :: POSIX
Classifier: Operating System :: Microsoft :: Windows
Classifier: Programming Language :: Python
Classifier: Programming Language :: Python :: 3
Classifier: Programming Language :: Python :: 3 :: Only
Classifier: Programming Language :: Python :: 3.7
Classifier: Programming Language :: Python :: 3.8
Classifier: Programming Language :: Python :: 3.9
Classifier: Programming Language :: Python :: 3.10
Classifier: Programming Language :: Python :: Implementation :: CPython
Classifier: Programming Language :: Python :: Implementation :: PyPy
Classifier: Topic :: Utilities
Requires-Python: >=3.7
License-File: LICENSE
License-File: AUTHORS.rst
